ifcdate/__init__.py
ifcdate/cli.py
ifcdate/core.py
ifcdate-0.1.3.dist-info/licenses/LICENSE
ifcdate-0.1.3.dist-info/METADATA
ifcdate-0.1.3.dist-info/WHEEL
ifcdate-0.1.3.dist-info/entry_points.txt
ifcdate-0.1.3.dist-info/top_level.txt
ifcdate-0.1.3.dist-info/RECORD
