Metadata-Version: 2.4
Name: ifcdate
Version: 0.1.3
Summary: Convert dates between Unix, Gregorian, and International Fixed Calendar
Author-email: Fabian Köll <koell.dev@google.com>
License-Expression: MIT
Requires-Python: >=3.8
License-File: LICENSE
Dynamic: license-file
